CHANGELOG.txt
LICENSE.txt
MANIFEST.in
README.txt
setup.py
Viz.egg-info/SOURCES.txt
Viz.egg-info/dependency_links.txt
Viz.egg-info/top_level.txt
Viz2D/__init__.py
Viz2D.egg-info/PKG-INFO
Viz2D.egg-info/SOURCES.txt
Viz2D.egg-info/dependency_links.txt
Viz2D.egg-info/top_level.txt